obtool/__init__.py
obtool-0.0.1.dist-info/LICENSE
obtool-0.0.1.dist-info/WHEEL
obtool-0.0.1.dist-info/METADATA
obtool-0.0.1.dist-info/RECORD
